{
  "generated_at": 1772964896,
  "input_csv": "/Users/seyong/Desktop/SNU/26W_MDIL_Intern/paper_search/paper_download/outputs/headless_ieee_elsevier_focus_20260308.csv",
  "sample_size": 9,
  "workers_requested": 1,
  "workers_effective": 1,
  "headless": true,
  "no_sandbox": true,
  "server_tuned": true,
  "single_process": "0",
  "humanized_browser": "1",
  "assume_institution_access": true,
  "startup_retries": 3,
  "timeout_sec": 15.0,
  "per_doi_deadline_sec": 45.0,
  "max_nav_attempts": 2,
  "publisher_cooldown_sec": 7.0,
  "global_start_spacing_sec": 1.5,
  "jitter_sec": [
    0.7,
    1.8
  ],
  "profile_mode": "auto",
  "profile_name": "Default",
  "persistent_profile_dir": "/Users/seyong/Desktop/SNU/26W_MDIL_Intern/paper_search/paper_download/outputs/.chrome_user_data",
  "worker_profile_root": "/tmp/seyong/landing_worker_profiles",
  "probe_page_mode": "reuse_page",
  "criteria": "success_landing only when expected publisher/target is reached, visible content is populated, article metadata or stable article markers exist, and no challenge/interstitial/blank heuristics fire.",
  "summary": {
    "total_valid": 9,
    "success_ratio": 0.8889,
    "classifier_counts": {
      "success_landing": 8,
      "publisher_error": 1
    },
    "outcome_counts": {
      "SUCCESS_ACCESS": 8,
      "FAIL_BLOCK": 1
    },
    "top_reason_codes": [
      [
        "content_populated",
        9
      ],
      [
        "expected_domain_match",
        9
      ],
      [
        "doi_match",
        8
      ],
      [
        "publisher_marker_present",
        8
      ],
      [
        "strong_meta_present",
        5
      ],
      [
        "publisher_error_marker",
        1
      ]
    ],
    "publisher_breakdown": [
      {
        "publisher": "elsevier",
        "sample_size": 5,
        "counts": {
          "success_landing": 5
        }
      },
      {
        "publisher": "ieee",
        "sample_size": 4,
        "counts": {
          "publisher_error": 1,
          "success_landing": 3
        }
      }
    ],
    "legacy_success_like_count": 8,
    "legacy_reclassified_non_success": [
      {
        "doi": "10.1109/pvsc.2017.8366874",
        "publisher": "2017 IEEE 44th Photovoltaic Specialist Conference (PVSC)",
        "final_url": "https://ieeexplore.ieee.org/document/8366874/",
        "title": "ieeexplore.ieee.org/document/8366874/",
        "classifier_state": "publisher_error",
        "reason_codes": [
          "content_populated",
          "expected_domain_match",
          "publisher_error_marker"
        ]
      }
    ],
    "p50_elapsed_ms": 21538.0,
    "p90_elapsed_ms": 40285.0,
    "domain_breakdown_top20": [
      {
        "domain": "ieeexplore.ieee.org",
        "sample_size": 4,
        "counts": {
          "publisher_error": 1,
          "success_landing": 3
        },
        "p50_elapsed_ms": 20481.0,
        "p90_elapsed_ms": 20670.0
      },
      {
        "domain": "www.sciencedirect.com",
        "sample_size": 4,
        "counts": {
          "success_landing": 4
        },
        "p50_elapsed_ms": 21677.5,
        "p90_elapsed_ms": 21817.0
      },
      {
        "domain": "www.cell.com",
        "sample_size": 1,
        "counts": {
          "success_landing": 1
        },
        "p50_elapsed_ms": 38885.0,
        "p90_elapsed_ms": 38885.0
      }
    ]
  },
  "publishers_covered": [
    "2017 IEEE 44th Photovoltaic Specialist Conference (PVSC)",
    "Elsevier BV",
    "Institute of Electrical and Electronics Engineers"
  ],
  "remaining_weak_spots": [],
  "output_jsonl": "/Users/seyong/Desktop/SNU/26W_MDIL_Intern/paper_search/paper_download/outputs/headless_ieee_elsevier_focus_20260308/results.jsonl",
  "artifact_dir": "/Users/seyong/Desktop/SNU/26W_MDIL_Intern/paper_search/paper_download/outputs/headless_ieee_elsevier_focus_20260308/artifacts",
  "failure_artifact_zip": "/Users/seyong/Desktop/SNU/26W_MDIL_Intern/paper_search/paper_download/outputs/headless_ieee_elsevier_focus_20260308/failures.zip",
  "success_artifact_zip": "/Users/seyong/Desktop/SNU/26W_MDIL_Intern/paper_search/paper_download/outputs/headless_ieee_elsevier_focus_20260308/successes.zip"
}